gptinterface/SimpleQuery.py
gptinterface/__init__.py
tests/__init__.py
GPTInterface-0.1.dist-info/LICENSE.txt
GPTInterface-0.1.dist-info/METADATA
GPTInterface-0.1.dist-info/WHEEL
GPTInterface-0.1.dist-info/top_level.txt
GPTInterface-0.1.dist-info/RECORD
